json_stock/__init__.py
json_stock/test.py
json_stock-0.2.6.dist-info/METADATA
json_stock-0.2.6.dist-info/WHEEL
json_stock-0.2.6.dist-info/top_level.txt
json_stock-0.2.6.dist-info/RECORD
